{
  "workshoptitle": "SecureOracle Taller 8.0",
  "help": "livelabs-help-license_us@oracle.com",
  "tutorials": [
    {
      "title": "Introducción",
      "description": "La introducción siempre es la segunda para LiveLabs. El título y el título del menú de contenido coinciden con la introducción.",
      "filename": "../../introduction/introduction_es.md"
    },
    {
      "title": "Laboratorio 1: Configuración del entorno",
      "description": "Verificar configuración de instancia informática",
      "filename": "https://oracle-livelabs.github.io/common/labs/verify-compute/verify-compute-ssh-and-novnc_es.md"
    },
    {
      "title": "Laboratorio 2: Inicialización del entorno",
      "description": "Inicializar entorno",
      "filename": "../../initialize-environment/initialize-environment_es.md"
    },
    {
      "title": "Laboratorio 3: Gestión del ciclo de vida de los empleados",
      "filename": "../../employeelm/employeelm_es.md"
    },
    {
      "title": "Laboratorio 4: Certificación de identidad",
      "filename": "../../idcert/idcert_es.md"
    },
    {
      "title": "Laboratorio 5: Uso de API de REST para OIM y OAM",
      "filename": "../../restapi/restapi_es.md"
    },
    {
      "title": "¿Necesita Ayuda?",
      "description": "Soluciones a problemas comunes e instrucciones para recibir ayuda en directo",
      "filename": "https://oracle-livelabs.github.io/common/labs/need-help/need-help-freetier_es.md"
    }
  ]
}